{
  "source": "exness",
  "year": 2020,
  "timeframe": "H1",
  "rows": 5914,
  "date_range": [
    "2020-01-02 01:00:00+00:00",
    "2020-12-31 17:00:00+00:00"
  ],
  "configs": {
    "NO_GOVERNANCE": {
      "trade_count": 889,
      "total_net_pnl": -1654.37,
      "gross_profit": 2387.46,
      "gross_loss": 4041.83,
      "profit_factor": 0.5907,
      "win_rate_pct": 35.88,
      "avg_win": 7.4842,
      "avg_loss": 7.0909,
      "payoff_ratio": 1.0555,
      "expectancy_per_trade": -1.8609,
      "max_dd_usd": 1697.09,
      "max_dd_pct": 16.9,
      "daily_dd_max_usd": 80.61,
      "sharpe": -5.2094,
      "sortino": -5.6247,
      "calmar": -0.9748,
      "recovery_factor": -0.9748,
      "longest_losing_streak": 14,
      "largest_single_loss": -78.53,
      "largest_single_win": 86.03,
      "mae_avg": 0.3242,
      "mfe_avg": 0.3697,
      "monthly_returns": {
        "2020-01": -139.87,
        "2020-02": -40.64,
        "2020-03": 42.53,
        "2020-04": -216.96,
        "2020-05": -163.79,
        "2020-06": -205.09,
        "2020-07": -174.92,
        "2020-08": -13.29,
        "2020-09": -169.92,
        "2020-10": -248.18,
        "2020-11": -149.09,
        "2020-12": -175.16
      },
      "profit_pct": -16.54,
      "lowest_equity": 8342.44,
      "blocked_count": 0,
      "blocked_winners": 0,
      "blocked_losers": 0,
      "exit_counts": {},
      "missed_profit_est": 0,
      "avoided_loss_est": 0,
      "overfiltering_ratio": 0,
      "funded_10pct_target_usd": 1000,
      "target_achieved": "False",
      "rule_breach": "True"
    },
    "SPRINT_9_9_3_2_PROP_FIRM_STRICT": {
      "trade_count": 0,
      "total_net_pnl": 0,
      "gross_profit": 0,
      "gross_loss": 0,
      "profit_factor": 0,
      "win_rate_pct": 0,
      "avg_win": 0,
      "avg_loss": 0,
      "payoff_ratio": 0,
      "expectancy_per_trade": 0,
      "max_dd_usd": 0,
      "max_dd_pct": 0,
      "daily_dd_max_usd": 0,
      "sharpe": 0,
      "sortino": 0,
      "calmar": 0,
      "recovery_factor": 0,
      "longest_losing_streak": 0,
      "largest_single_loss": 0,
      "largest_single_win": 0,
      "mae_avg": 0,
      "mfe_avg": 0,
      "monthly_returns": {},
      "profit_pct": 0,
      "lowest_equity": 10000,
      "blocked_count": 4423,
      "blocked_winners": 1582,
      "blocked_losers": 2841,
      "exit_counts": {},
      "missed_profit_est": 0.0,
      "avoided_loss_est": 0.0,
      "overfiltering_ratio": 0.0,
      "funded_10pct_target_usd": 1000,
      "target_achieved": false,
      "rule_breach": false
    },
    "SPRINT_9_9_3_3_RETAIL_SAFE": {
      "trade_count": 227,
      "total_net_pnl": 829.93,
      "gross_profit": 882.13,
      "gross_loss": 52.2,
      "profit_factor": 16.8979,
      "win_rate_pct": 92.51,
      "avg_win": 4.2006,
      "avg_loss": 4.3503,
      "payoff_ratio": 0.9656,
      "expectancy_per_trade": 3.6561,
      "max_dd_usd": 25.36,
      "max_dd_pct": 0.24,
      "daily_dd_max_usd": 25.36,
      "sharpe": 7.8949,
      "sortino": 5.6047,
      "calmar": 32.7231,
      "recovery_factor": 32.7231,
      "longest_losing_streak": 2,
      "largest_single_loss": -25.36,
      "largest_single_win": 48.43,
      "mae_avg": 0.1259,
      "mfe_avg": 0.6299,
      "monthly_returns": {
        "2020-01": 119.79,
        "2020-02": 77.8,
        "2020-03": 193.43,
        "2020-05": 43.27,
        "2020-06": 39.5,
        "2020-07": 36.13,
        "2020-08": 88.86,
        "2020-09": 59.63,
        "2020-10": 30.16,
        "2020-11": 66.3,
        "2020-12": 75.07
      },
      "profit_pct": 8.3,
      "lowest_equity": 9999.63,
      "blocked_count": 3220,
      "blocked_winners": 943,
      "blocked_losers": 2277,
      "exit_counts": {
        "PARTIAL_CLOSE": 34,
        "TIGHT_TRAIL": 38,
        "CLOSE": 43,
        "MOVE_BE": 77
      },
      "missed_profit_est": 1723.84,
      "avoided_loss_est": 4162.45,
      "overfiltering_ratio": 0.4141,
      "funded_10pct_target_usd": 1000,
      "target_achieved": "False",
      "rule_breach": "False"
    },
    "SPRINT_9_9_3_3_PROP_FIRM_STRICT": {
      "trade_count": 0,
      "total_net_pnl": 0,
      "gross_profit": 0,
      "gross_loss": 0,
      "profit_factor": 0,
      "win_rate_pct": 0,
      "avg_win": 0,
      "avg_loss": 0,
      "payoff_ratio": 0,
      "expectancy_per_trade": 0,
      "max_dd_usd": 0,
      "max_dd_pct": 0,
      "daily_dd_max_usd": 0,
      "sharpe": 0,
      "sortino": 0,
      "calmar": 0,
      "recovery_factor": 0,
      "longest_losing_streak": 0,
      "largest_single_loss": 0,
      "largest_single_win": 0,
      "mae_avg": 0,
      "mfe_avg": 0,
      "monthly_returns": {},
      "profit_pct": 0,
      "lowest_equity": 10000,
      "blocked_count": 4423,
      "blocked_winners": 1582,
      "blocked_losers": 2841,
      "exit_counts": {},
      "missed_profit_est": 0.0,
      "avoided_loss_est": 0.0,
      "overfiltering_ratio": 0.0,
      "funded_10pct_target_usd": 1000,
      "target_achieved": false,
      "rule_breach": false
    },
    "SPRINT_9_9_3_3_INSTITUTIONAL": {
      "trade_count": 0,
      "total_net_pnl": 0,
      "gross_profit": 0,
      "gross_loss": 0,
      "profit_factor": 0,
      "win_rate_pct": 0,
      "avg_win": 0,
      "avg_loss": 0,
      "payoff_ratio": 0,
      "expectancy_per_trade": 0,
      "max_dd_usd": 0,
      "max_dd_pct": 0,
      "daily_dd_max_usd": 0,
      "sharpe": 0,
      "sortino": 0,
      "calmar": 0,
      "recovery_factor": 0,
      "longest_losing_streak": 0,
      "largest_single_loss": 0,
      "largest_single_win": 0,
      "mae_avg": 0,
      "mfe_avg": 0,
      "monthly_returns": {},
      "profit_pct": 0,
      "lowest_equity": 10000,
      "blocked_count": 4423,
      "blocked_winners": 1582,
      "blocked_losers": 2841,
      "exit_counts": {},
      "missed_profit_est": 0.0,
      "avoided_loss_est": 0.0,
      "overfiltering_ratio": 0.0,
      "funded_10pct_target_usd": 1000,
      "target_achieved": false,
      "rule_breach": false
    }
  },
  "cost_stress": {
    "NORMAL_COST": {
      "trade_count": 0,
      "total_net_pnl": 0,
      "gross_profit": 0,
      "gross_loss": 0,
      "profit_factor": 0,
      "win_rate_pct": 0,
      "avg_win": 0,
      "avg_loss": 0,
      "payoff_ratio": 0,
      "expectancy_per_trade": 0,
      "max_dd_usd": 0,
      "max_dd_pct": 0,
      "daily_dd_max_usd": 0,
      "sharpe": 0,
      "sortino": 0,
      "calmar": 0,
      "recovery_factor": 0,
      "longest_losing_streak": 0,
      "largest_single_loss": 0,
      "largest_single_win": 0,
      "mae_avg": 0,
      "mfe_avg": 0,
      "monthly_returns": {},
      "profit_pct": 0,
      "lowest_equity": 10000,
      "target_achieved": false,
      "rule_breach": false
    },
    "HIGH_SPREAD": {
      "trade_count": 0,
      "total_net_pnl": 0,
      "gross_profit": 0,
      "gross_loss": 0,
      "profit_factor": 0,
      "win_rate_pct": 0,
      "avg_win": 0,
      "avg_loss": 0,
      "payoff_ratio": 0,
      "expectancy_per_trade": 0,
      "max_dd_usd": 0,
      "max_dd_pct": 0,
      "daily_dd_max_usd": 0,
      "sharpe": 0,
      "sortino": 0,
      "calmar": 0,
      "recovery_factor": 0,
      "longest_losing_streak": 0,
      "largest_single_loss": 0,
      "largest_single_win": 0,
      "mae_avg": 0,
      "mfe_avg": 0,
      "monthly_returns": {},
      "profit_pct": 0,
      "lowest_equity": 10000,
      "target_achieved": false,
      "rule_breach": false
    },
    "HIGH_SLIPPAGE": {
      "trade_count": 0,
      "total_net_pnl": 0,
      "gross_profit": 0,
      "gross_loss": 0,
      "profit_factor": 0,
      "win_rate_pct": 0,
      "avg_win": 0,
      "avg_loss": 0,
      "payoff_ratio": 0,
      "expectancy_per_trade": 0,
      "max_dd_usd": 0,
      "max_dd_pct": 0,
      "daily_dd_max_usd": 0,
      "sharpe": 0,
      "sortino": 0,
      "calmar": 0,
      "recovery_factor": 0,
      "longest_losing_streak": 0,
      "largest_single_loss": 0,
      "largest_single_win": 0,
      "mae_avg": 0,
      "mfe_avg": 0,
      "monthly_returns": {},
      "profit_pct": 0,
      "lowest_equity": 10000,
      "target_achieved": false,
      "rule_breach": false
    },
    "LOW_LIQUIDITY": {
      "trade_count": 0,
      "total_net_pnl": 0,
      "gross_profit": 0,
      "gross_loss": 0,
      "profit_factor": 0,
      "win_rate_pct": 0,
      "avg_win": 0,
      "avg_loss": 0,
      "payoff_ratio": 0,
      "expectancy_per_trade": 0,
      "max_dd_usd": 0,
      "max_dd_pct": 0,
      "daily_dd_max_usd": 0,
      "sharpe": 0,
      "sortino": 0,
      "calmar": 0,
      "recovery_factor": 0,
      "longest_losing_streak": 0,
      "largest_single_loss": 0,
      "largest_single_win": 0,
      "mae_avg": 0,
      "mfe_avg": 0,
      "monthly_returns": {},
      "profit_pct": 0,
      "lowest_equity": 10000,
      "target_achieved": false,
      "rule_breach": false
    },
    "WORST_BROKER": {
      "trade_count": 0,
      "total_net_pnl": 0,
      "gross_profit": 0,
      "gross_loss": 0,
      "profit_factor": 0,
      "win_rate_pct": 0,
      "avg_win": 0,
      "avg_loss": 0,
      "payoff_ratio": 0,
      "expectancy_per_trade": 0,
      "max_dd_usd": 0,
      "max_dd_pct": 0,
      "daily_dd_max_usd": 0,
      "sharpe": 0,
      "sortino": 0,
      "calmar": 0,
      "recovery_factor": 0,
      "longest_losing_streak": 0,
      "largest_single_loss": 0,
      "largest_single_win": 0,
      "mae_avg": 0,
      "mfe_avg": 0,
      "monthly_returns": {},
      "profit_pct": 0,
      "lowest_equity": 10000,
      "target_achieved": false,
      "rule_breach": false
    },
    "HARSH_COMBINED": {
      "trade_count": 0,
      "total_net_pnl": 0,
      "gross_profit": 0,
      "gross_loss": 0,
      "profit_factor": 0,
      "win_rate_pct": 0,
      "avg_win": 0,
      "avg_loss": 0,
      "payoff_ratio": 0,
      "expectancy_per_trade": 0,
      "max_dd_usd": 0,
      "max_dd_pct": 0,
      "daily_dd_max_usd": 0,
      "sharpe": 0,
      "sortino": 0,
      "calmar": 0,
      "recovery_factor": 0,
      "longest_losing_streak": 0,
      "largest_single_loss": 0,
      "largest_single_win": 0,
      "mae_avg": 0,
      "mfe_avg": 0,
      "monthly_returns": {},
      "profit_pct": 0,
      "lowest_equity": 10000,
      "target_achieved": false,
      "rule_breach": false
    }
  }
}